tasa
tests
