Metadata-Version: 1.1
Name: tasa
Version: 0.2.3
Summary: A simple framework for distributed task workflow using redis.
Home-page: https://github.com/PaulMcMillan/tasa
Author: Paul McMillan
Author-email: paul@mcmillan.ws
License: Simplified BSD
Platform: UNKNOWN
Classifier: Environment :: Console
Classifier: Intended Audience :: Developers
Classifier: License :: OSI Approved :: BSD License
Classifier: Operating System :: POSIX
Classifier: Programming Language :: Python :: 2.7
Classifier: Programming Language :: Python :: Implementation :: CPython
Classifier: Programming Language :: Python :: Implementation :: PyPy
